e3/archive.py
e3/cve.py
e3/date.py
e3/decorator.py
e3/diff.py
e3/dsse.py
e3/env.py
e3/error.py
e3/fingerprint.py
e3/fs.py
e3/hash.py
e3/json.py
e3/log.py
e3/main.py
e3/maven.py
e3/mypy.py
e3/npm.py
e3/platform.py
e3/py.typed
e3/pytest.py
e3/spdx.py
e3/sys.py
e3/text.py
e3/yaml.py
e3/anod/__init__.py
e3/anod/buildspace.py
e3/anod/checkout.py
e3/anod/context.py
e3/anod/deps.py
e3/anod/driver.py
e3/anod/error.py
e3/anod/helper.py
e3/anod/loader.py
e3/anod/package.py
e3/anod/qualifier.py
e3/anod/qualifiers_manager.py
e3/anod/queries.py
e3/anod/spec.py
e3/anod/status.py
e3/anod/action/__init__.py
e3/anod/sandbox/__init__.py
e3/anod/sandbox/main.py
e3/anod/sandbox/scripts.py
e3/collection/__init__.py
e3/collection/dag.py
e3/collection/toggleable_bool.py
e3/collection/trie.py
e3/electrolyt/__init__.py
e3/electrolyt/entry_point.py
e3/electrolyt/host.py
e3/electrolyt/plan.py
e3/electrolyt/run.py
e3/encoding/__init__.py
e3/encoding/vex.py
e3/event/__init__.py
e3/event/handler/__init__.py
e3/event/handler/file.py
e3/event/handler/logging.py
e3/event/handler/s3.py
e3/event/handler/smtp.py
e3/job/__init__.py
e3/job/scheduler.py
e3/job/walk.py
e3/mock/__init__.py
e3/mock/env.py
e3/mock/os/__init__.py
e3/mock/os/process.py
e3/net/__init__.py
e3/net/http.py
e3/net/smtp.py
e3/net/token.py
e3/os/__init__.py
e3/os/fs.py
e3/os/platform.py
e3/os/process.py
e3/os/timezone.py
e3/os/data/rlimit-aarch64-darwin
e3/os/data/rlimit-aarch64-linux
e3/os/data/rlimit-ppc-aix
e3/os/data/rlimit-ppc-linux
e3/os/data/rlimit-sparc-solaris
e3/os/data/rlimit-x86-linux
e3/os/data/rlimit-x86-solaris
e3/os/data/rlimit-x86-windows
e3/os/data/rlimit-x86_64-darwin
e3/os/data/rlimit-x86_64-linux
e3/os/data/rlimit-x86_64-windows
e3/os/windows/__init__.py
e3/os/windows/fs.py
e3/os/windows/native_api.py
e3/os/windows/object.py
e3/os/windows/process.py
e3/platform_db/__init__.py
e3/platform_db/knowledge_base.py
e3/python/__init__.py
e3/python/pypi.py
e3/python/pypiscript.py
e3/python/wheel.py
e3/slsa/__init__.py
e3_core-22.10.0.dist-info/licenses/COPYING3
e3_core-22.10.0.dist-info/METADATA
e3_core-22.10.0.dist-info/WHEEL
e3_core-22.10.0.dist-info/entry_points.txt
e3_core-22.10.0.dist-info/top_level.txt
e3_core-22.10.0.dist-info/RECORD
