Metadata-Version: 2.4
Name: e3-core
Version: 22.10.0
Summary: E3 core. Tools and library for building and testing software
Author: AdaCore's IT Team
License: GPLv3
Project-URL: Repository, https://github.com/AdaCore/e3-core
Classifier: Development Status :: 5 - Production/Stable
Classifier: Intended Audience :: Developers
Classifier: License :: OSI Approved :: GNU General Public License v3 (GPLv3)
Classifier: Programming Language :: Python :: 3.9
Classifier: Programming Language :: Python :: 3.10
Classifier: Programming Language :: Python :: 3.11
Classifier: Programming Language :: Python :: 3.12
Classifier: Topic :: Software Development :: Build Tools
License-File: COPYING3
Requires-Dist: colorama
Requires-Dist: pyyaml
Requires-Dist: python-dateutil
Requires-Dist: requests
Requires-Dist: requests-cache
Requires-Dist: requests_toolbelt
Requires-Dist: tqdm
Requires-Dist: stevedore>1.20.0
Requires-Dist: setuptools
Requires-Dist: packaging
Requires-Dist: resolvelib
Requires-Dist: psutil; sys_platform == "win32"
Requires-Dist: psutil; sys_platform == "linux"
Requires-Dist: psutil; sys_platform == "linux2"
Requires-Dist: psutil; sys_platform == "darwin"
Requires-Dist: distro; sys_platform == "linux"
Requires-Dist: distro; sys_platform == "linux2"
Provides-Extra: test
Requires-Dist: mock; extra == "test"
Requires-Dist: requests-mock; extra == "test"
Requires-Dist: pytest; extra == "test"
Requires-Dist: pytest-html; extra == "test"
Requires-Dist: pytest-socket; extra == "test"
Requires-Dist: ansi2html; extra == "test"
Requires-Dist: ptyprocess; sys_platform != "win32" and extra == "test"
Requires-Dist: requests-mock; extra == "test"
Provides-Extra: check
Requires-Dist: mypy==1.14.1; extra == "check"
Requires-Dist: pytest; extra == "check"
Requires-Dist: bandit; extra == "check"
Requires-Dist: pip-audit; extra == "check"
Requires-Dist: types-colorama; extra == "check"
Requires-Dist: types-mock; extra == "check"
Requires-Dist: types-psutil; extra == "check"
Requires-Dist: types-python-dateutil; extra == "check"
Requires-Dist: types-PyYAML; extra == "check"
Requires-Dist: types-requests; extra == "check"
Requires-Dist: types-setuptools; extra == "check"
Requires-Dist: distro; sys_platform == "darwin" and extra == "check"
Dynamic: license-file
